rtorch/__init__.py
rtorch/biject.py
rtorch/known.py
rtorch/robject.py
rtorch/bijections/__init__.py
rtorch/bijections/torch.csv
caravanrtorch-0.1.0.dist-info/METADATA
caravanrtorch-0.1.0.dist-info/WHEEL
caravanrtorch-0.1.0.dist-info/top_level.txt
caravanrtorch-0.1.0.dist-info/RECORD
