Metadata-Version: 2.4
Name: caravanrtorch
Version: 0.1.0
Requires-Python: >=3.10
Requires-Dist: filelock>=3.18.0
Requires-Dist: fsspec>=2025.7.0
Requires-Dist: jedi>=0.19.0
Requires-Dist: Jinja2>=3.0.0
Requires-Dist: MarkupSafe>=3.0.2
Requires-Dist: mpmath>=1.3.0
Requires-Dist: networkx>=3.4.2
Requires-Dist: numpy>=2.0.0
Requires-Dist: parso>=0.8.4
Requires-Dist: setuptools>=80.9.0
Requires-Dist: torch>=2.5.1
Requires-Dist: sympy>=1.13.0
Requires-Dist: typeguard>=4.4.0
Requires-Dist: typing_extensions>=4.14.1
